sapiadapter/__init__.py
sapiadapter/s_cache.py
sapiadapter/s_cleanup.py
sapiadapter/s_config.py
sapiadapter/s_db.py
sapiadapter/s_log.py
sapiadapter/s_net.py
sapiadapter/s_util.py
sapiadapter/sapiadapter.py
sapiadapter-0.38.394.dist-info/METADATA
sapiadapter-0.38.394.dist-info/WHEEL
sapiadapter-0.38.394.dist-info/RECORD
