Metadata-Version: 2.1
Name: sapiadapter
Version: 0.38.394
Summary: 
Author: Zafar Iqbal
Author-email: zaf@sparc.space
Requires-Python: >=3.10,<3.12
Classifier: Programming Language :: Python :: 3
Classifier: Programming Language :: Python :: 3.10
Classifier: Programming Language :: Python :: 3.11
Requires-Dist: requests (>=2.28.2,<3.0.0)
